{
  "name": "shotgun",
  "word": "identifier",
  "rules": {
    "source_file": {
      "type": "REPEAT",
      "content": {
        "type": "SYMBOL",
        "name": "_item"
      }
    },
    "_item": {
      "type": "CHOICE",
      "members": [
        {
          "type": "SYMBOL",
          "name": "uses_statement"
        },
        {
          "type": "SYMBOL",
          "name": "struct_definition"
        },
        {
          "type": "SYMBOL",
          "name": "variant_definition"
        },
        {
          "type": "SYMBOL",
          "name": "trait_definition"
        },
        {
          "type": "SYMBOL",
          "name": "impl_block"
        },
        {
          "type": "SYMBOL",
          "name": "method_definition"
        },
        {
          "type": "SYMBOL",
          "name": "function_definition"
        },
        {
          "type": "SYMBOL",
          "name": "error_definition"
        }
      ]
    },
    "uses_statement": {
      "type": "SEQ",
      "members": [
        {
          "type": "STRING",
          "value": "uses"
        },
        {
          "type": "STRING",
          "value": ":"
        },
        {
          "type": "CHOICE",
          "members": [
            {
              "type": "SYMBOL",
              "name": "inline_import_list"
            },
            {
              "type": "SYMBOL",
              "name": "dash_import_list"
            }
          ]
        }
      ]
    },
    "inline_import_list": {
      "type": "SEQ",
      "members": [
        {
          "type": "SYMBOL",
          "name": "import_path"
        },
        {
          "type": "REPEAT",
          "content": {
            "type": "SEQ",
            "members": [
              {
                "type": "STRING",
                "value": ","
              },
              {
                "type": "SYMBOL",
                "name": "import_path"
              }
            ]
          }
        }
      ]
    },
    "dash_import_list": {
      "type": "REPEAT1",
      "content": {
        "type": "SYMBOL",
        "name": "dash_import_item"
      }
    },
    "dash_import_item": {
      "type": "SEQ",
      "members": [
        {
          "type": "STRING",
          "value": "-"
        },
        {
          "type": "SYMBOL",
          "name": "import_path"
        }
      ]
    },
    "import_path": {
      "type": "SEQ",
      "members": [
        {
          "type": "SYMBOL",
          "name": "identifier"
        },
        {
          "type": "REPEAT",
          "content": {
            "type": "SEQ",
            "members": [
              {
                "type": "STRING",
                "value": "."
              },
              {
                "type": "SYMBOL",
                "name": "identifier"
              }
            ]
          }
        }
      ]
    },
    "comment": {
      "type": "TOKEN",
      "content": {
        "type": "SEQ",
        "members": [
          {
            "type": "STRING",
            "value": "//"
          },
          {
            "type": "PATTERN",
            "value": ".*"
          }
        ]
      }
    },
    "struct_definition": {
      "type": "SEQ",
      "members": [
        {
          "type": "FIELD",
          "name": "name",
          "content": {
            "type": "SYMBOL",
            "name": "type_identifier"
          }
        },
        {
          "type": "STRING",
          "value": "::"
        },
        {
          "type": "STRING",
          "value": "struct"
        },
        {
          "type": "STRING",
          "value": "{"
        },
        {
          "type": "REPEAT",
          "content": {
            "type": "SYMBOL",
            "name": "field_definition"
          }
        },
        {
          "type": "STRING",
          "value": "}"
        }
      ]
    },
    "variant_definition": {
      "type": "SEQ",
      "members": [
        {
          "type": "FIELD",
          "name": "name",
          "content": {
            "type": "SYMBOL",
            "name": "type_identifier"
          }
        },
        {
          "type": "CHOICE",
          "members": [
            {
              "type": "SYMBOL",
              "name": "type_parameters"
            },
            {
              "type": "BLANK"
            }
          ]
        },
        {
          "type": "STRING",
          "value": "::"
        },
        {
          "type": "STRING",
          "value": "variant"
        },
        {
          "type": "STRING",
          "value": "{"
        },
        {
          "type": "REPEAT",
          "content": {
            "type": "SYMBOL",
            "name": "variant_case"
          }
        },
        {
          "type": "STRING",
          "value": "}"
        }
      ]
    },
    "variant_case": {
      "type": "SEQ",
      "members": [
        {
          "type": "FIELD",
          "name": "name",
          "content": {
            "type": "SYMBOL",
            "name": "type_identifier"
          }
        },
        {
          "type": "CHOICE",
          "members": [
            {
              "type": "SEQ",
              "members": [
                {
                  "type": "STRING",
                  "value": "{"
                },
                {
                  "type": "REPEAT",
                  "content": {
                    "type": "SYMBOL",
                    "name": "field_definition"
                  }
                },
                {
                  "type": "STRING",
                  "value": "}"
                }
              ]
            },
            {
              "type": "BLANK"
            }
          ]
        }
      ]
    },
    "type_parameters": {
      "type": "SEQ",
      "members": [
        {
          "type": "STRING",
          "value": "<"
        },
        {
          "type": "SYMBOL",
          "name": "identifier"
        },
        {
          "type": "REPEAT",
          "content": {
            "type": "SEQ",
            "members": [
              {
                "type": "STRING",
                "value": ","
              },
              {
                "type": "SYMBOL",
                "name": "identifier"
              }
            ]
          }
        },
        {
          "type": "STRING",
          "value": ">"
        }
      ]
    },
    "field_definition": {
      "type": "SEQ",
      "members": [
        {
          "type": "FIELD",
          "name": "name",
          "content": {
            "type": "SYMBOL",
            "name": "identifier"
          }
        },
        {
          "type": "FIELD",
          "name": "type",
          "content": {
            "type": "SYMBOL",
            "name": "_type"
          }
        }
      ]
    },
    "trait_definition": {
      "type": "SEQ",
      "members": [
        {
          "type": "FIELD",
          "name": "name",
          "content": {
            "type": "SYMBOL",
            "name": "type_identifier"
          }
        },
        {
          "type": "STRING",
          "value": "::"
        },
        {
          "type": "STRING",
          "value": "trait"
        },
        {
          "type": "STRING",
          "value": "{"
        },
        {
          "type": "REPEAT",
          "content": {
            "type": "SYMBOL",
            "name": "trait_method"
          }
        },
        {
          "type": "STRING",
          "value": "}"
        }
      ]
    },
    "trait_method": {
      "type": "SEQ",
      "members": [
        {
          "type": "FIELD",
          "name": "name",
          "content": {
            "type": "SYMBOL",
            "name": "identifier"
          }
        },
        {
          "type": "STRING",
          "value": "("
        },
        {
          "type": "CHOICE",
          "members": [
            {
              "type": "SYMBOL",
              "name": "parameter_list"
            },
            {
              "type": "BLANK"
            }
          ]
        },
        {
          "type": "STRING",
          "value": ")"
        },
        {
          "type": "CHOICE",
          "members": [
            {
              "type": "SYMBOL",
              "name": "_type"
            },
            {
              "type": "BLANK"
            }
          ]
        }
      ]
    },
    "impl_block": {
      "type": "SEQ",
      "members": [
        {
          "type": "FIELD",
          "name": "type",
          "content": {
            "type": "SYMBOL",
            "name": "type_identifier"
          }
        },
        {
          "type": "STRING",
          "value": "::"
        },
        {
          "type": "STRING",
          "value": "impl"
        },
        {
          "type": "FIELD",
          "name": "trait",
          "content": {
            "type": "SYMBOL",
            "name": "type_identifier"
          }
        },
        {
          "type": "STRING",
          "value": "{"
        },
        {
          "type": "REPEAT",
          "content": {
            "type": "SYMBOL",
            "name": "impl_method"
          }
        },
        {
          "type": "STRING",
          "value": "}"
        }
      ]
    },
    "impl_method": {
      "type": "SEQ",
      "members": [
        {
          "type": "FIELD",
          "name": "name",
          "content": {
            "type": "SYMBOL",
            "name": "identifier"
          }
        },
        {
          "type": "STRING",
          "value": "("
        },
        {
          "type": "CHOICE",
          "members": [
            {
              "type": "SYMBOL",
              "name": "parameter_list"
            },
            {
              "type": "BLANK"
            }
          ]
        },
        {
          "type": "STRING",
          "value": ")"
        },
        {
          "type": "CHOICE",
          "members": [
            {
              "type": "SYMBOL",
              "name": "_type"
            },
            {
              "type": "BLANK"
            }
          ]
        },
        {
          "type": "SYMBOL",
          "name": "block"
        }
      ]
    },
    "method_definition": {
      "type": "SEQ",
      "members": [
        {
          "type": "FIELD",
          "name": "type",
          "content": {
            "type": "SYMBOL",
            "name": "type_identifier"
          }
        },
        {
          "type": "STRING",
          "value": "::"
        },
        {
          "type": "FIELD",
          "name": "name",
          "content": {
            "type": "SYMBOL",
            "name": "identifier"
          }
        },
        {
          "type": "STRING",
          "value": "("
        },
        {
          "type": "CHOICE",
          "members": [
            {
              "type": "SYMBOL",
              "name": "parameter_list"
            },
            {
              "type": "BLANK"
            }
          ]
        },
        {
          "type": "STRING",
          "value": ")"
        },
        {
          "type": "CHOICE",
          "members": [
            {
              "type": "SYMBOL",
              "name": "_return_type"
            },
            {
              "type": "BLANK"
            }
          ]
        },
        {
          "type": "SYMBOL",
          "name": "block"
        }
      ]
    },
    "function_definition": {
      "type": "SEQ",
      "members": [
        {
          "type": "STRING",
          "value": "fn"
        },
        {
          "type": "FIELD",
          "name": "name",
          "content": {
            "type": "SYMBOL",
            "name": "identifier"
          }
        },
        {
          "type": "CHOICE",
          "members": [
            {
              "type": "SEQ",
              "members": [
                {
                  "type": "STRING",
                  "value": "("
                },
                {
                  "type": "CHOICE",
                  "members": [
                    {
                      "type": "SYMBOL",
                      "name": "parameter_list"
                    },
                    {
                      "type": "BLANK"
                    }
                  ]
                },
                {
                  "type": "STRING",
                  "value": ")"
                }
              ]
            },
            {
              "type": "BLANK"
            }
          ]
        },
        {
          "type": "CHOICE",
          "members": [
            {
              "type": "SYMBOL",
              "name": "_return_type"
            },
            {
              "type": "BLANK"
            }
          ]
        },
        {
          "type": "SYMBOL",
          "name": "block"
        }
      ]
    },
    "error_definition": {
      "type": "SEQ",
      "members": [
        {
          "type": "FIELD",
          "name": "name",
          "content": {
            "type": "SYMBOL",
            "name": "type_identifier"
          }
        },
        {
          "type": "STRING",
          "value": "::"
        },
        {
          "type": "STRING",
          "value": "error"
        },
        {
          "type": "STRING",
          "value": "{"
        },
        {
          "type": "REPEAT",
          "content": {
            "type": "SYMBOL",
            "name": "field_definition"
          }
        },
        {
          "type": "STRING",
          "value": "}"
        }
      ]
    },
    "_return_type": {
      "type": "SEQ",
      "members": [
        {
          "type": "SYMBOL",
          "name": "_type"
        },
        {
          "type": "CHOICE",
          "members": [
            {
              "type": "SEQ",
              "members": [
                {
                  "type": "STRING",
                  "value": "or"
                },
                {
                  "type": "STRING",
                  "value": "Error"
                }
              ]
            },
            {
              "type": "BLANK"
            }
          ]
        }
      ]
    },
    "parameter_list": {
      "type": "SEQ",
      "members": [
        {
          "type": "SYMBOL",
          "name": "parameter"
        },
        {
          "type": "REPEAT",
          "content": {
            "type": "SEQ",
            "members": [
              {
                "type": "STRING",
                "value": ","
              },
              {
                "type": "SYMBOL",
                "name": "parameter"
              }
            ]
          }
        },
        {
          "type": "CHOICE",
          "members": [
            {
              "type": "STRING",
              "value": ","
            },
            {
              "type": "BLANK"
            }
          ]
        }
      ]
    },
    "parameter": {
      "type": "CHOICE",
      "members": [
        {
          "type": "STRING",
          "value": "self"
        },
        {
          "type": "SEQ",
          "members": [
            {
              "type": "SYMBOL",
              "name": "_type"
            },
            {
              "type": "FIELD",
              "name": "name",
              "content": {
                "type": "SYMBOL",
                "name": "identifier"
              }
            }
          ]
        }
      ]
    },
    "_type": {
      "type": "CHOICE",
      "members": [
        {
          "type": "SYMBOL",
          "name": "primitive_type"
        },
        {
          "type": "SYMBOL",
          "name": "optional_type"
        },
        {
          "type": "SYMBOL",
          "name": "array_type"
        },
        {
          "type": "SYMBOL",
          "name": "channel_type"
        },
        {
          "type": "SYMBOL",
          "name": "type_identifier"
        }
      ]
    },
    "primitive_type": {
      "type": "CHOICE",
      "members": [
        {
          "type": "STRING",
          "value": "str"
        },
        {
          "type": "STRING",
          "value": "int"
        },
        {
          "type": "STRING",
          "value": "bool"
        },
        {
          "type": "STRING",
          "value": "f32"
        },
        {
          "type": "STRING",
          "value": "f64"
        },
        {
          "type": "STRING",
          "value": "u32"
        },
        {
          "type": "STRING",
          "value": "u64"
        }
      ]
    },
    "optional_type": {
      "type": "SEQ",
      "members": [
        {
          "type": "CHOICE",
          "members": [
            {
              "type": "SYMBOL",
              "name": "primitive_type"
            },
            {
              "type": "SYMBOL",
              "name": "type_identifier"
            }
          ]
        },
        {
          "type": "STRING",
          "value": "?"
        }
      ]
    },
    "array_type": {
      "type": "SEQ",
      "members": [
        {
          "type": "CHOICE",
          "members": [
            {
              "type": "SYMBOL",
              "name": "primitive_type"
            },
            {
              "type": "SYMBOL",
              "name": "type_identifier"
            }
          ]
        },
        {
          "type": "STRING",
          "value": "["
        },
        {
          "type": "STRING",
          "value": "]"
        }
      ]
    },
    "channel_type": {
      "type": "SEQ",
      "members": [
        {
          "type": "STRING",
          "value": "chan"
        },
        {
          "type": "SYMBOL",
          "name": "_type"
        }
      ]
    },
    "type_identifier": {
      "type": "PATTERN",
      "value": "[A-Z][a-zA-Z0-9_]*"
    },
    "block": {
      "type": "SEQ",
      "members": [
        {
          "type": "STRING",
          "value": "{"
        },
        {
          "type": "REPEAT",
          "content": {
            "type": "SYMBOL",
            "name": "_statement"
          }
        },
        {
          "type": "STRING",
          "value": "}"
        }
      ]
    },
    "_statement": {
      "type": "CHOICE",
      "members": [
        {
          "type": "SYMBOL",
          "name": "variable_declaration"
        },
        {
          "type": "SYMBOL",
          "name": "inferred_declaration"
        },
        {
          "type": "SYMBOL",
          "name": "const_declaration"
        },
        {
          "type": "SYMBOL",
          "name": "return_statement"
        },
        {
          "type": "SYMBOL",
          "name": "if_statement"
        },
        {
          "type": "SYMBOL",
          "name": "for_statement"
        },
        {
          "type": "SYMBOL",
          "name": "while_statement"
        },
        {
          "type": "SYMBOL",
          "name": "match_statement"
        },
        {
          "type": "SYMBOL",
          "name": "go_statement"
        },
        {
          "type": "SYMBOL",
          "name": "expression_statement"
        }
      ]
    },
    "variable_declaration": {
      "type": "SEQ",
      "members": [
        {
          "type": "SYMBOL",
          "name": "_type"
        },
        {
          "type": "FIELD",
          "name": "name",
          "content": {
            "type": "SYMBOL",
            "name": "identifier"
          }
        },
        {
          "type": "STRING",
          "value": "="
        },
        {
          "type": "SYMBOL",
          "name": "_expression"
        }
      ]
    },
    "inferred_declaration": {
      "type": "SEQ",
      "members": [
        {
          "type": "FIELD",
          "name": "name",
          "content": {
            "type": "SYMBOL",
            "name": "identifier"
          }
        },
        {
          "type": "STRING",
          "value": ":="
        },
        {
          "type": "SYMBOL",
          "name": "_expression"
        }
      ]
    },
    "const_declaration": {
      "type": "SEQ",
      "members": [
        {
          "type": "STRING",
          "value": "const"
        },
        {
          "type": "FIELD",
          "name": "name",
          "content": {
            "type": "SYMBOL",
            "name": "identifier"
          }
        },
        {
          "type": "STRING",
          "value": "="
        },
        {
          "type": "SYMBOL",
          "name": "_expression"
        }
      ]
    },
    "expression_statement": {
      "type": "SYMBOL",
      "name": "_expression"
    },
    "return_statement": {
      "type": "PREC_RIGHT",
      "value": 0,
      "content": {
        "type": "SEQ",
        "members": [
          {
            "type": "STRING",
            "value": "return"
          },
          {
            "type": "CHOICE",
            "members": [
              {
                "type": "SYMBOL",
                "name": "_expression"
              },
              {
                "type": "BLANK"
              }
            ]
          }
        ]
      }
    },
    "if_statement": {
      "type": "PREC_RIGHT",
      "value": 0,
      "content": {
        "type": "SEQ",
        "members": [
          {
            "type": "STRING",
            "value": "if"
          },
          {
            "type": "SYMBOL",
            "name": "_expression"
          },
          {
            "type": "SYMBOL",
            "name": "block"
          },
          {
            "type": "CHOICE",
            "members": [
              {
                "type": "SEQ",
                "members": [
                  {
                    "type": "STRING",
                    "value": "else"
                  },
                  {
                    "type": "CHOICE",
                    "members": [
                      {
                        "type": "SYMBOL",
                        "name": "if_statement"
                      },
                      {
                        "type": "SYMBOL",
                        "name": "block"
                      }
                    ]
                  }
                ]
              },
              {
                "type": "BLANK"
              }
            ]
          }
        ]
      }
    },
    "for_statement": {
      "type": "SEQ",
      "members": [
        {
          "type": "STRING",
          "value": "for"
        },
        {
          "type": "SYMBOL",
          "name": "identifier"
        },
        {
          "type": "STRING",
          "value": "in"
        },
        {
          "type": "SYMBOL",
          "name": "_expression"
        },
        {
          "type": "SYMBOL",
          "name": "block"
        }
      ]
    },
    "while_statement": {
      "type": "SEQ",
      "members": [
        {
          "type": "STRING",
          "value": "while"
        },
        {
          "type": "SYMBOL",
          "name": "_expression"
        },
        {
          "type": "SYMBOL",
          "name": "block"
        }
      ]
    },
    "match_statement": {
      "type": "SEQ",
      "members": [
        {
          "type": "STRING",
          "value": "match"
        },
        {
          "type": "SYMBOL",
          "name": "_expression"
        },
        {
          "type": "STRING",
          "value": "{"
        },
        {
          "type": "REPEAT",
          "content": {
            "type": "SYMBOL",
            "name": "match_arm"
          }
        },
        {
          "type": "STRING",
          "value": "}"
        }
      ]
    },
    "match_arm": {
      "type": "SEQ",
      "members": [
        {
          "type": "SYMBOL",
          "name": "pattern"
        },
        {
          "type": "STRING",
          "value": "->"
        },
        {
          "type": "CHOICE",
          "members": [
            {
              "type": "SYMBOL",
              "name": "block"
            },
            {
              "type": "SYMBOL",
              "name": "_expression"
            }
          ]
        }
      ]
    },
    "pattern": {
      "type": "SEQ",
      "members": [
        {
          "type": "SYMBOL",
          "name": "identifier"
        },
        {
          "type": "CHOICE",
          "members": [
            {
              "type": "SYMBOL",
              "name": "identifier"
            },
            {
              "type": "BLANK"
            }
          ]
        }
      ]
    },
    "go_statement": {
      "type": "SEQ",
      "members": [
        {
          "type": "STRING",
          "value": "go"
        },
        {
          "type": "SYMBOL",
          "name": "_expression"
        }
      ]
    },
    "_expression": {
      "type": "CHOICE",
      "members": [
        {
          "type": "SYMBOL",
          "name": "binary_expression"
        },
        {
          "type": "SYMBOL",
          "name": "unary_expression"
        },
        {
          "type": "SYMBOL",
          "name": "call_expression"
        },
        {
          "type": "SYMBOL",
          "name": "member_expression"
        },
        {
          "type": "SYMBOL",
          "name": "or_expression"
        },
        {
          "type": "SYMBOL",
          "name": "struct_literal"
        },
        {
          "type": "SYMBOL",
          "name": "array_literal"
        },
        {
          "type": "SYMBOL",
          "name": "identifier"
        },
        {
          "type": "SYMBOL",
          "name": "number"
        },
        {
          "type": "SYMBOL",
          "name": "string"
        },
        {
          "type": "SYMBOL",
          "name": "bool_literal"
        },
        {
          "type": "SYMBOL",
          "name": "none_literal"
        },
        {
          "type": "SYMBOL",
          "name": "paren_expression"
        },
        {
          "type": "SYMBOL",
          "name": "assignment_expression"
        }
      ]
    },
    "paren_expression": {
      "type": "SEQ",
      "members": [
        {
          "type": "STRING",
          "value": "("
        },
        {
          "type": "SYMBOL",
          "name": "_expression"
        },
        {
          "type": "STRING",
          "value": ")"
        }
      ]
    },
    "binary_expression": {
      "type": "CHOICE",
      "members": [
        {
          "type": "PREC_LEFT",
          "value": 1,
          "content": {
            "type": "SEQ",
            "members": [
              {
                "type": "SYMBOL",
                "name": "_expression"
              },
              {
                "type": "STRING",
                "value": "||"
              },
              {
                "type": "SYMBOL",
                "name": "_expression"
              }
            ]
          }
        },
        {
          "type": "PREC_LEFT",
          "value": 2,
          "content": {
            "type": "SEQ",
            "members": [
              {
                "type": "SYMBOL",
                "name": "_expression"
              },
              {
                "type": "STRING",
                "value": "and"
              },
              {
                "type": "SYMBOL",
                "name": "_expression"
              }
            ]
          }
        },
        {
          "type": "PREC_LEFT",
          "value": 3,
          "content": {
            "type": "SEQ",
            "members": [
              {
                "type": "SYMBOL",
                "name": "_expression"
              },
              {
                "type": "CHOICE",
                "members": [
                  {
                    "type": "STRING",
                    "value": "=="
                  },
                  {
                    "type": "STRING",
                    "value": "!="
                  },
                  {
                    "type": "STRING",
                    "value": "<"
                  },
                  {
                    "type": "STRING",
                    "value": ">"
                  },
                  {
                    "type": "STRING",
                    "value": "<="
                  },
                  {
                    "type": "STRING",
                    "value": ">="
                  },
                  {
                    "type": "STRING",
                    "value": "in"
                  }
                ]
              },
              {
                "type": "SYMBOL",
                "name": "_expression"
              }
            ]
          }
        },
        {
          "type": "PREC_LEFT",
          "value": 4,
          "content": {
            "type": "SEQ",
            "members": [
              {
                "type": "SYMBOL",
                "name": "_expression"
              },
              {
                "type": "CHOICE",
                "members": [
                  {
                    "type": "STRING",
                    "value": "+"
                  },
                  {
                    "type": "STRING",
                    "value": "-"
                  }
                ]
              },
              {
                "type": "SYMBOL",
                "name": "_expression"
              }
            ]
          }
        },
        {
          "type": "PREC_LEFT",
          "value": 5,
          "content": {
            "type": "SEQ",
            "members": [
              {
                "type": "SYMBOL",
                "name": "_expression"
              },
              {
                "type": "CHOICE",
                "members": [
                  {
                    "type": "STRING",
                    "value": "*"
                  },
                  {
                    "type": "STRING",
                    "value": "/"
                  },
                  {
                    "type": "STRING",
                    "value": "%"
                  }
                ]
              },
              {
                "type": "SYMBOL",
                "name": "_expression"
              }
            ]
          }
        }
      ]
    },
    "unary_expression": {
      "type": "PREC",
      "value": 6,
      "content": {
        "type": "SEQ",
        "members": [
          {
            "type": "STRING",
            "value": "not"
          },
          {
            "type": "SYMBOL",
            "name": "_expression"
          }
        ]
      }
    },
    "or_expression": {
      "type": "PREC_LEFT",
      "value": 1,
      "content": {
        "type": "SEQ",
        "members": [
          {
            "type": "SYMBOL",
            "name": "_expression"
          },
          {
            "type": "STRING",
            "value": "or"
          },
          {
            "type": "CHOICE",
            "members": [
              {
                "type": "SYMBOL",
                "name": "_expression"
              },
              {
                "type": "SYMBOL",
                "name": "or_return"
              },
              {
                "type": "SYMBOL",
                "name": "or_error"
              },
              {
                "type": "SYMBOL",
                "name": "or_wait"
              }
            ]
          }
        ]
      }
    },
    "or_return": {
      "type": "PREC_RIGHT",
      "value": 0,
      "content": {
        "type": "SEQ",
        "members": [
          {
            "type": "STRING",
            "value": "return"
          },
          {
            "type": "CHOICE",
            "members": [
              {
                "type": "SYMBOL",
                "name": "_expression"
              },
              {
                "type": "BLANK"
              }
            ]
          }
        ]
      }
    },
    "or_error": {
      "type": "PREC_RIGHT",
      "value": 0,
      "content": {
        "type": "SEQ",
        "members": [
          {
            "type": "STRING",
            "value": "error"
          },
          {
            "type": "SYMBOL",
            "name": "type_identifier"
          },
          {
            "type": "CHOICE",
            "members": [
              {
                "type": "SYMBOL",
                "name": "struct_literal"
              },
              {
                "type": "BLANK"
              }
            ]
          }
        ]
      }
    },
    "or_wait": {
      "type": "PREC_RIGHT",
      "value": 0,
      "content": {
        "type": "SEQ",
        "members": [
          {
            "type": "STRING",
            "value": "wait"
          },
          {
            "type": "STRING",
            "value": "("
          },
          {
            "type": "SYMBOL",
            "name": "_expression"
          },
          {
            "type": "STRING",
            "value": ")"
          }
        ]
      }
    },
    "assignment_expression": {
      "type": "PREC_RIGHT",
      "value": 0,
      "content": {
        "type": "SEQ",
        "members": [
          {
            "type": "SYMBOL",
            "name": "_expression"
          },
          {
            "type": "CHOICE",
            "members": [
              {
                "type": "STRING",
                "value": "="
              },
              {
                "type": "STRING",
                "value": "+="
              },
              {
                "type": "STRING",
                "value": "-="
              },
              {
                "type": "STRING",
                "value": "*="
              },
              {
                "type": "STRING",
                "value": "/="
              }
            ]
          },
          {
            "type": "SYMBOL",
            "name": "_expression"
          }
        ]
      }
    },
    "call_expression": {
      "type": "PREC",
      "value": 8,
      "content": {
        "type": "SEQ",
        "members": [
          {
            "type": "SYMBOL",
            "name": "_expression"
          },
          {
            "type": "STRING",
            "value": "("
          },
          {
            "type": "CHOICE",
            "members": [
              {
                "type": "SYMBOL",
                "name": "argument_list"
              },
              {
                "type": "BLANK"
              }
            ]
          },
          {
            "type": "STRING",
            "value": ")"
          }
        ]
      }
    },
    "member_expression": {
      "type": "PREC",
      "value": 9,
      "content": {
        "type": "SEQ",
        "members": [
          {
            "type": "SYMBOL",
            "name": "_expression"
          },
          {
            "type": "STRING",
            "value": "."
          },
          {
            "type": "FIELD",
            "name": "member",
            "content": {
              "type": "SYMBOL",
              "name": "identifier"
            }
          }
        ]
      }
    },
    "argument_list": {
      "type": "SEQ",
      "members": [
        {
          "type": "SYMBOL",
          "name": "_expression"
        },
        {
          "type": "REPEAT",
          "content": {
            "type": "SEQ",
            "members": [
              {
                "type": "STRING",
                "value": ","
              },
              {
                "type": "SYMBOL",
                "name": "_expression"
              }
            ]
          }
        },
        {
          "type": "CHOICE",
          "members": [
            {
              "type": "STRING",
              "value": ","
            },
            {
              "type": "BLANK"
            }
          ]
        }
      ]
    },
    "struct_literal": {
      "type": "PREC",
      "value": 7,
      "content": {
        "type": "SEQ",
        "members": [
          {
            "type": "SYMBOL",
            "name": "type_identifier"
          },
          {
            "type": "STRING",
            "value": "{"
          },
          {
            "type": "CHOICE",
            "members": [
              {
                "type": "SYMBOL",
                "name": "field_init_list"
              },
              {
                "type": "BLANK"
              }
            ]
          },
          {
            "type": "STRING",
            "value": "}"
          }
        ]
      }
    },
    "field_init_list": {
      "type": "SEQ",
      "members": [
        {
          "type": "SYMBOL",
          "name": "field_init"
        },
        {
          "type": "REPEAT",
          "content": {
            "type": "SEQ",
            "members": [
              {
                "type": "STRING",
                "value": ","
              },
              {
                "type": "SYMBOL",
                "name": "field_init"
              }
            ]
          }
        },
        {
          "type": "CHOICE",
          "members": [
            {
              "type": "STRING",
              "value": ","
            },
            {
              "type": "BLANK"
            }
          ]
        }
      ]
    },
    "field_init": {
      "type": "SEQ",
      "members": [
        {
          "type": "FIELD",
          "name": "name",
          "content": {
            "type": "SYMBOL",
            "name": "identifier"
          }
        },
        {
          "type": "STRING",
          "value": ":"
        },
        {
          "type": "SYMBOL",
          "name": "_expression"
        }
      ]
    },
    "array_literal": {
      "type": "SEQ",
      "members": [
        {
          "type": "STRING",
          "value": "["
        },
        {
          "type": "CHOICE",
          "members": [
            {
              "type": "SEQ",
              "members": [
                {
                  "type": "SYMBOL",
                  "name": "_expression"
                },
                {
                  "type": "REPEAT",
                  "content": {
                    "type": "SEQ",
                    "members": [
                      {
                        "type": "STRING",
                        "value": ","
                      },
                      {
                        "type": "SYMBOL",
                        "name": "_expression"
                      }
                    ]
                  }
                },
                {
                  "type": "CHOICE",
                  "members": [
                    {
                      "type": "STRING",
                      "value": ","
                    },
                    {
                      "type": "BLANK"
                    }
                  ]
                }
              ]
            },
            {
              "type": "BLANK"
            }
          ]
        },
        {
          "type": "STRING",
          "value": "]"
        }
      ]
    },
    "identifier": {
      "type": "PATTERN",
      "value": "[a-z_][a-zA-Z0-9_]*"
    },
    "number": {
      "type": "PATTERN",
      "value": "\\d+(\\.\\d+)?"
    },
    "string": {
      "type": "SEQ",
      "members": [
        {
          "type": "STRING",
          "value": "\""
        },
        {
          "type": "REPEAT",
          "content": {
            "type": "CHOICE",
            "members": [
              {
                "type": "SYMBOL",
                "name": "string_content"
              },
              {
                "type": "SYMBOL",
                "name": "escape_sequence"
              },
              {
                "type": "SYMBOL",
                "name": "interpolation"
              }
            ]
          }
        },
        {
          "type": "STRING",
          "value": "\""
        }
      ]
    },
    "string_content": {
      "type": "PATTERN",
      "value": "[^\"\\\\{]+"
    },
    "escape_sequence": {
      "type": "PATTERN",
      "value": "\\\\[\\\\nrt\"{]"
    },
    "interpolation": {
      "type": "SEQ",
      "members": [
        {
          "type": "STRING",
          "value": "{"
        },
        {
          "type": "SYMBOL",
          "name": "_expression"
        },
        {
          "type": "STRING",
          "value": "}"
        }
      ]
    },
    "bool_literal": {
      "type": "CHOICE",
      "members": [
        {
          "type": "STRING",
          "value": "true"
        },
        {
          "type": "STRING",
          "value": "false"
        }
      ]
    },
    "none_literal": {
      "type": "STRING",
      "value": "none"
    }
  },
  "extras": [
    {
      "type": "PATTERN",
      "value": "\\s"
    },
    {
      "type": "SYMBOL",
      "name": "comment"
    }
  ],
  "conflicts": [
    [
      "type_identifier",
      "identifier"
    ]
  ],
  "precedences": [],
  "externals": [],
  "inline": [],
  "supertypes": []
}
